fiqus/MainFiQuS.py
fiqus/__init__.py
fiqus/data/DataConductor.py
fiqus/data/DataFiQuS.py
fiqus/data/DataFiQuSCCT.py
fiqus/data/DataFiQuSConductor.py
fiqus/data/DataFiQuSConductorAC_CC.py
fiqus/data/DataFiQuSConductorAC_Rutherford.py
fiqus/data/DataFiQuSConductorAC_Strand.py
fiqus/data/DataFiQuSHomogenizedConductor.py
fiqus/data/DataFiQuSMultipole.py
fiqus/data/DataFiQuSPancake3D.py
fiqus/data/DataModelCommon.py
fiqus/data/DataMultipole.py
fiqus/data/DataRoxieParser.py
fiqus/data/DataSettings.py
fiqus/data/DataWindingsCCT.py
fiqus/data/RegionsModelFiQuS.py
fiqus/data/__init__.py
fiqus/geom_generators/GeometryCCT.py
fiqus/geom_generators/GeometryConductorAC_CC.py
fiqus/geom_generators/GeometryConductorAC_Rutherford.py
fiqus/geom_generators/GeometryConductorAC_Strand.py
fiqus/geom_generators/GeometryConductorAC_Strand_RutherfordCopy.py
fiqus/geom_generators/GeometryHomogenizedConductor.py
fiqus/geom_generators/GeometryMultipole.py
fiqus/geom_generators/GeometryPancake3D.py
fiqus/geom_generators/GeometryPancake3DUtils.py
fiqus/geom_generators/__init__.py
fiqus/getdp_runners/RunGetdpCCT.py
fiqus/getdp_runners/RunGetdpConductorAC_CC.py
fiqus/getdp_runners/RunGetdpConductorAC_Rutherford.py
fiqus/getdp_runners/RunGetdpConductorAC_Strand.py
fiqus/getdp_runners/RunGetdpHomogenizedConductor.py
fiqus/getdp_runners/RunGetdpMultipole.py
fiqus/getdp_runners/RunGetdpPancake3D.py
fiqus/getdp_runners/__init__.py
fiqus/mains/MainCCT.py
fiqus/mains/MainConductorAC_CC.py
fiqus/mains/MainConductorAC_Rutherford.py
fiqus/mains/MainConductorAC_Strand.py
fiqus/mains/MainHomogenizedConductor.py
fiqus/mains/MainMultipole.py
fiqus/mains/MainPancake3D.py
fiqus/mains/__init__.py
fiqus/mesh_generators/MeshCCT.py
fiqus/mesh_generators/MeshConductorAC_CC.py
fiqus/mesh_generators/MeshConductorAC_Rutherford.py
fiqus/mesh_generators/MeshConductorAC_Strand.py
fiqus/mesh_generators/MeshConductorAC_Strand_RutherfordCopy.py
fiqus/mesh_generators/MeshHomogenizedConductor.py
fiqus-2026.1.3.dist-info/licenses/LICENSE.txt
fiqus-2026.1.3.dist-info/METADATA
fiqus-2026.1.3.dist-info/WHEEL
fiqus-2026.1.3.dist-info/top_level.txt
fiqus-2026.1.3.dist-info/RECORD
