Metadata-Version: 2.4
Name: fiqus
Version: 2026.1.3
Summary: Source code for STEAM FiQuS tool
Home-page: https://gitlab.cern.ch/steam/fiqus
Author: STEAM Team
Author-email: steam-team@cern.ch
Keywords: STEAM,FiQuS,CERN
Classifier: Programming Language :: Python :: 3.11
Requires-Python: >=3.11
License-File: LICENSE.txt
Requires-Dist: gmsh==4.15.0
Requires-Dist: h5py<4,>=3.10
Requires-Dist: Jinja2<4,>=3.1
Requires-Dist: matplotlib<4,>=3.8
Requires-Dist: mplcursors<1,>=0.5
Requires-Dist: numpy<2,>=1.26
Requires-Dist: pandas<3,>=2.2
Requires-Dist: pydantic<3,>=2.6
Requires-Dist: ruamel.yaml<1,>=0.18
Requires-Dist: scipy<2,>=1.14
Requires-Dist: tqdm<5,>=4.66
Provides-Extra: docs
Requires-Dist: griffe==0.42.0; extra == "docs"
Requires-Dist: markdown==3.5.2; extra == "docs"
Requires-Dist: markdown-include==0.8.1; extra == "docs"
Requires-Dist: mkdocs-git-revision-date-localized-plugin==1.2.4; extra == "docs"
Requires-Dist: mkdocs-include-markdown-plugin==6.0.4; extra == "docs"
Requires-Dist: mkdocs-material==9.5.13; extra == "docs"
Requires-Dist: mkdocstrings-python==1.9.0; extra == "docs"
Requires-Dist: mkdocs-autorefs==1.3.1; extra == "docs"
Provides-Extra: tests
Requires-Dist: coverage==7.4.4; extra == "tests"
Requires-Dist: coverage-badge==1.1.0; extra == "tests"
Requires-Dist: flake8==7.0.0; extra == "tests"
Requires-Dist: mypy==1.9.0; extra == "tests"
Requires-Dist: pylint==3.1.0; extra == "tests"
Requires-Dist: pytest==8.1.1; extra == "tests"
Requires-Dist: pytest-cov==4.1.0; extra == "tests"
Requires-Dist: pytest-subtests==0.12.1; extra == "tests"
Provides-Extra: build
Requires-Dist: setuptools==69.2.0; extra == "build"
Requires-Dist: wheel==0.45.1; extra == "build"
Requires-Dist: twine==6.0.1; extra == "build"
Provides-Extra: all
Requires-Dist: gmsh==4.15.0; extra == "all"
Requires-Dist: h5py<4,>=3.10; extra == "all"
Requires-Dist: Jinja2<4,>=3.1; extra == "all"
Requires-Dist: matplotlib<4,>=3.8; extra == "all"
Requires-Dist: mplcursors<1,>=0.5; extra == "all"
Requires-Dist: numpy<2,>=1.26; extra == "all"
Requires-Dist: pandas<3,>=2.2; extra == "all"
Requires-Dist: pydantic<3,>=2.6; extra == "all"
Requires-Dist: ruamel.yaml<1,>=0.18; extra == "all"
Requires-Dist: scipy<2,>=1.14; extra == "all"
Requires-Dist: tqdm<5,>=4.66; extra == "all"
Requires-Dist: griffe==0.42.0; extra == "all"
Requires-Dist: markdown==3.5.2; extra == "all"
Requires-Dist: markdown-include==0.8.1; extra == "all"
Requires-Dist: mkdocs-git-revision-date-localized-plugin==1.2.4; extra == "all"
Requires-Dist: mkdocs-include-markdown-plugin==6.0.4; extra == "all"
Requires-Dist: mkdocs-material==9.5.13; extra == "all"
Requires-Dist: mkdocstrings-python==1.9.0; extra == "all"
Requires-Dist: mkdocs-autorefs==1.3.1; extra == "all"
Requires-Dist: coverage==7.4.4; extra == "all"
Requires-Dist: coverage-badge==1.1.0; extra == "all"
Requires-Dist: flake8==7.0.0; extra == "all"
Requires-Dist: mypy==1.9.0; extra == "all"
Requires-Dist: pylint==3.1.0; extra == "all"
Requires-Dist: pytest==8.1.1; extra == "all"
Requires-Dist: pytest-cov==4.1.0; extra == "all"
Requires-Dist: pytest-subtests==0.12.1; extra == "all"
Requires-Dist: setuptools==69.2.0; extra == "all"
Requires-Dist: wheel==0.45.1; extra == "all"
Requires-Dist: twine==6.0.1; extra == "all"
Dynamic: author
Dynamic: author-email
Dynamic: classifier
Dynamic: description
Dynamic: description-content-type
Dynamic: home-page
Dynamic: keywords
Dynamic: license-file
Dynamic: provides-extra
Dynamic: requires-dist
Dynamic: requires-python
Dynamic: summary
